<?xml version='1.0' encoding='utf-8'?>
<ns0:leistung xmlns:ns0="http://xoev.de/schemata/xzufi/2_2_0" xmlns:xsi="http://www.w3.org/2001/XMLSchema-instance"><ns0:id schemeAgencyID="B100019" schemeAgencyName="TSA Public Service GmbH" schemeID="TSA_LEIKA_OID" schemeName="Leika ObjektID">105435577</ns0:id><ns0:idSekundaer schemeAgencyID="GK_LEIKA" schemeAgencyName="GK LeiKa" schemeID="LEIKA_LEISTUNG_SCHLUESSEL" schemeName="LeiKa Leistungsschlüssel" schemeVersionID="2">99159015166000</ns0:idSekundaer><ns0:struktur xsi:type="xzufi:LeistungsstrukturObjektMitVerrichtung"><ns0:leistungsgruppierung><ns0:leistungsgruppierungLeiKa listURI="urn:de:fim:leika:leistungsgruppierung" listVersionID="20231229"><code>159</code></ns0:leistungsgruppierungLeiKa></ns0:leistungsgruppierung><ns0:leistungsobjektID>105435576</ns0:leistungsobjektID><ns0:verrichtung><ns0:verrichtungLeiKa listURI="urn:de:fim:leika:verrichtung" listVersionID="20230523"><code>166</code><name>Anhörung</name></ns0:verrichtungLeiKa></ns0:verrichtung></ns0:struktur><ns0:modulText><ns0:leikaTextmodul listURI="urn:de:xzufi:codeliste:leistungstextmodulleika" listVersionID="20240216"><code>02</code></ns0:leikaTextmodul><ns0:inhalt languageCode="de-DE">Öffentlichkeitsbeteiligung im Rahmen der Planfeststellung bei Bauvorhaben der Eisenbahn des Bundes Anhörung</ns0:inhalt><ns0:inhalt languageCode="en">Public participation in the planning approval process for federal railroad construction projects Consultation</ns0:inhalt></ns0:modulText><ns0:modulText><ns0:leikaTextmodul listURI="urn:de:xzufi:codeliste:leistungstextmodulleika" listVersionID="20240216"><code>03</code></ns0:leikaTextmodul><ns0:inhalt languageCode="en">Raise objections to planned federal railroad construction projects and submit comments</ns0:inhalt><ns0:inhalt languageCode="de-DE">Einwendungen gegen geplante Bauvorhaben der Eisenbahn des Bundes erheben und Stellungnahmen abgeben</ns0:inhalt></ns0:modulText><ns0:modulText><ns0:positionDarstellung>15</ns0:positionDarstellung><ns0:leikaTextmodul listURI="urn:de:xzufi:codeliste:leistungstextmodulleika" listVersionID="20240216"><code>18</code></ns0:leikaTextmodul><ns0:inhalt languageCode="de-DE">&lt;p&gt;Eisenbahn-Bundesamt (EBA)&lt;/p&gt;</ns0:inhalt></ns0:modulText><ns0:modulText><ns0:positionDarstellung>4</ns0:positionDarstellung><ns0:leikaTextmodul listURI="urn:de:xzufi:codeliste:leistungstextmodulleika" listVersionID="20240216"><code>07</code></ns0:leikaTextmodul><ns0:weiterfuehrenderLink languageCode="de-DE"><ns0:uri>https://www.gesetze-im-internet.de/aeg_1994/__18.html</ns0:uri><ns0:titel>§ 18 Absatz 1 Satz 3 Allgemeines Eisenbahngesetz (AEG)</ns0:titel><ns0:positionDarstellung>0</ns0:positionDarstellung></ns0:weiterfuehrenderLink><ns0:weiterfuehrenderLink languageCode="de-DE"><ns0:uri>https://www.gesetze-im-internet.de/vwvfg/__73.html</ns0:uri><ns0:titel>§ 73 Absatz 2 bis 8 Verwaltungsverfahrensgesetz (VwVfG)</ns0:titel><ns0:positionDarstellung>1</ns0:positionDarstellung></ns0:weiterfuehrenderLink><ns0:weiterfuehrenderLink languageCode="de-DE"><ns0:uri>https://www.gesetze-im-internet.de/uvpg/__18.html</ns0:uri><ns0:titel>§§ 18 bis 22 Gesetz über die Umweltverträglichkeitsprüfung (UVPG)</ns0:titel><ns0:positionDarstellung>2</ns0:positionDarstellung></ns0:weiterfuehrenderLink><ns0:weiterfuehrenderLink languageCode="de-DE"><ns0:uri>https://www.gesetze-im-internet.de/aeg_1994/__18a.html</ns0:uri><ns0:titel>§ 18a Allgemeines Eisenbahngesetz (AEG)</ns0:titel><ns0:positionDarstellung>3</ns0:positionDarstellung></ns0:weiterfuehrenderLink><ns0:weiterfuehrenderLink languageCode="de-DE"><ns0:uri>https://www.gesetze-im-internet.de/vwvfg/__73.html</ns0:uri><ns0:titel>§ 74 Absatz 4 bis 5 Verwaltungsverfahrensgesetz (VwVfG)</ns0:titel><ns0:positionDarstellung>4</ns0:positionDarstellung></ns0:weiterfuehrenderLink></ns0:modulText><ns0:modulText><ns0:positionDarstellung>1</ns0:positionDarstellung><ns0:leikaTextmodul listURI="urn:de:xzufi:codeliste:leistungstextmodulleika" listVersionID="20240216"><code>18</code></ns0:leikaTextmodul><ns0:inhalt languageCode="de-DE">Weiterleitungsdienst: Deep-Link zum Ursprungsportal</ns0:inhalt><ns0:weiterfuehrenderLink languageCode="de-DE"><ns0:uri>https://leika.zfinder.de/portaldeeplink/?tsa_leistung_id=105435577&amp;tsa_sprache=de_DE</ns0:uri><ns0:titel>Öffentlichkeitsbeteiligung im Rahmen der Planfeststellung bei Bauvorhaben der Eisenbahn des Bundes Anhörung</ns0:titel><ns0:beschreibung>Anzeige der Leistung im Ursprungsportal</ns0:beschreibung><ns0:positionDarstellung>1</ns0:positionDarstellung></ns0:weiterfuehrenderLink><ns0:weiterfuehrenderLink languageCode="en"><ns0:uri>https://leika.zfinder.de/portaldeeplink/?tsa_leistung_id=105435577&amp;tsa_sprache=en</ns0:uri><ns0:titel>Public participation in the planning approval process for federal railroad construction projects Consultation</ns0:titel><ns0:beschreibung>Anzeige der Leistung im Ursprungsportal</ns0:beschreibung><ns0:positionDarstellung>1</ns0:positionDarstellung></ns0:weiterfuehrenderLink></ns0:modulText><ns0:modulTextIndividuell><ns0:positionDarstellung>19</ns0:positionDarstellung><ns0:individuellesTextmodultyp listURI="individuell" listVersionID="unbestimmt"><code>STATUSKATALOG</code><name>Status Katalogeintrag</name></ns0:individuellesTextmodultyp><ns0:inhalt languageCode="de-DE">6</ns0:inhalt><ns0:inhalt languageCode="en">6</ns0:inhalt></ns0:modulTextIndividuell><ns0:modulBegriffImKontext><ns0:begriffImKontext><ns0:begriff languageCode="de-DE">Stellungnahme</ns0:begriff></ns0:begriffImKontext><ns0:begriffImKontext><ns0:begriff languageCode="de-DE">Träger öffentlicher Belange</ns0:begriff></ns0:begriffImKontext><ns0:begriffImKontext><ns0:begriff languageCode="de-DE">Genehmigung</ns0:begriff></ns0:begriffImKontext><ns0:begriffImKontext><ns0:begriff languageCode="de-DE">Eisenbahn-Bundesamt</ns0:begriff></ns0:begriffImKontext><ns0:begriffImKontext><ns0:begriff languageCode="de-DE">EBA</ns0:begriff></ns0:begriffImKontext><ns0:begriffImKontext><ns0:begriff languageCode="de-DE">Planfeststellung</ns0:begriff></ns0:begriffImKontext><ns0:begriffImKontext><ns0:begriff languageCode="de-DE">Planfeststellungsverfahren</ns0:begriff></ns0:begriffImKontext><ns0:begriffImKontext><ns0:begriff languageCode="de-DE">Plangenehmigungsverfahren</ns0:begriff></ns0:begriffImKontext><ns0:begriffImKontext><ns0:begriff languageCode="de-DE">Plangenehmigung</ns0:begriff></ns0:begriffImKontext><ns0:begriffImKontext><ns0:begriff languageCode="de-DE">Neubau</ns0:begriff></ns0:begriffImKontext><ns0:begriffImKontext><ns0:begriff languageCode="de-DE">Anhörungsverfahren</ns0:begriff></ns0:begriffImKontext><ns0:begriffImKontext><ns0:begriff languageCode="de-DE">Öffentlichkeitsbeteiligung</ns0:begriff></ns0:begriffImKontext><ns0:begriffImKontext><ns0:begriff languageCode="de-DE">Planfeststellungsbeschluss</ns0:begriff></ns0:begriffImKontext><ns0:begriffImKontext><ns0:begriff languageCode="de-DE">Einwendung</ns0:begriff></ns0:begriffImKontext><ns0:begriffImKontext><ns0:begriff languageCode="de-DE">Infrastruktur</ns0:begriff></ns0:begriffImKontext><ns0:begriffImKontext><ns0:begriff languageCode="de-DE">Mittelbahnsteig</ns0:begriff></ns0:begriffImKontext><ns0:begriffImKontext><ns0:begriff languageCode="de-DE">Umweltverträglichkeitsprüfung</ns0:begriff></ns0:begriffImKontext><ns0:begriffImKontext><ns0:begriff languageCode="de-DE">Ausbau</ns0:begriff></ns0:begriffImKontext><ns0:begriffImKontext><ns0:begriff languageCode="de-DE">Schienenwege</ns0:begriff></ns0:begriffImKontext><ns0:begriffImKontext><ns0:begriff languageCode="de-DE">Planänderung</ns0:begriff></ns0:begriffImKontext><ns0:begriffImKontext><ns0:begriff languageCode="de-DE">Rückbau</ns0:begriff></ns0:begriffImKontext><ns0:begriffImKontext><ns0:begriff languageCode="de-DE">UVP</ns0:begriff></ns0:begriffImKontext><ns0:begriffImKontext><ns0:begriff languageCode="de-DE">Einwand</ns0:begriff></ns0:begriffImKontext><ns0:begriffImKontext><ns0:begriff languageCode="de-DE">Einwender</ns0:begriff></ns0:begriffImKontext><ns0:begriffImKontext><ns0:begriff languageCode="de-DE">Einwenderin</ns0:begriff></ns0:begriffImKontext><ns0:begriffImKontext><ns0:begriff languageCode="de-DE">Abstellbahnhof</ns0:begriff></ns0:begriffImKontext><ns0:begriffImKontext><ns0:begriff languageCode="de-DE">Ausbaustrecke</ns0:begriff></ns0:begriffImKontext><ns0:begriffImKontext><ns0:begriff languageCode="de-DE">Außenbahnsteig</ns0:begriff></ns0:begriffImKontext><ns0:begriffImKontext><ns0:begriff languageCode="de-DE">Bahnhof</ns0:begriff></ns0:begriffImKontext><ns0:begriffImKontext><ns0:begriff languageCode="de-DE">Bahnsteig</ns0:begriff></ns0:begriffImKontext><ns0:begriffImKontext><ns0:begriff languageCode="de-DE">Bahnsteigverlängerung</ns0:begriff></ns0:begriffImKontext><ns0:begriffImKontext><ns0:begriff languageCode="de-DE">Bahnübergang</ns0:begriff></ns0:begriffImKontext><ns0:begriffImKontext><ns0:begriff languageCode="de-DE">Behördenbeteiligung</ns0:begriff></ns0:begriffImKontext><ns0:begriffImKontext><ns0:begriff languageCode="de-DE">BeteiligungsverfahrenBetriebswerk</ns0:begriff></ns0:begriffImKontext><ns0:begriffImKontext><ns0:begriff languageCode="de-DE">dreigleisiger Ausbau</ns0:begriff></ns0:begriffImKontext><ns0:begriffImKontext><ns0:begriff languageCode="de-DE">eingleisiger Ausbau</ns0:begriff></ns0:begriffImKontext><ns0:begriffImKontext><ns0:begriff languageCode="de-DE">Eisenbahnknoten</ns0:begriff></ns0:begriffImKontext><ns0:begriffImKontext><ns0:begriff languageCode="de-DE">Eisenbahntunnel</ns0:begriff></ns0:begriffImKontext><ns0:begriffImKontext><ns0:begriff languageCode="de-DE">Eisenbahnüberführung</ns0:begriff></ns0:begriffImKontext><ns0:begriffImKontext><ns0:begriff languageCode="de-DE">Elektrifizierung</ns0:begriff></ns0:begriffImKontext><ns0:begriffImKontext><ns0:begriff languageCode="de-DE">elektronisches Stellwerk</ns0:begriff></ns0:begriffImKontext><ns0:begriffImKontext><ns0:begriff languageCode="de-DE">ESTW</ns0:begriff></ns0:begriffImKontext><ns0:begriffImKontext><ns0:begriff languageCode="de-DE">GSM-R Basisstation</ns0:begriff></ns0:begriffImKontext><ns0:begriffImKontext><ns0:begriff languageCode="de-DE">Haltepunkt</ns0:begriff></ns0:begriffImKontext><ns0:begriffImKontext><ns0:begriff languageCode="de-DE">Kreuzungsbauwerk</ns0:begriff></ns0:begriffImKontext><ns0:begriffImKontext><ns0:begriff languageCode="de-DE">Lärmsanierung</ns0:begriff></ns0:begriffImKontext><ns0:begriffImKontext><ns0:begriff languageCode="de-DE">Lärmschutzwand</ns0:begriff></ns0:begriffImKontext><ns0:begriffImKontext><ns0:begriff languageCode="de-DE">Mittelbahnsteig</ns0:begriff></ns0:begriffImKontext><ns0:begriffImKontext><ns0:begriff languageCode="de-DE">Neubaustrecke</ns0:begriff></ns0:begriffImKontext><ns0:begriffImKontext><ns0:begriff languageCode="de-DE">Rangierbahnhof</ns0:begriff></ns0:begriffImKontext><ns0:begriffImKontext><ns0:begriff languageCode="de-DE">Stellwerk</ns0:begriff></ns0:begriffImKontext><ns0:begriffImKontext><ns0:begriff languageCode="de-DE">Umschlaganlage</ns0:begriff></ns0:begriffImKontext><ns0:begriffImKontext><ns0:begriff languageCode="de-DE">Verkehrsstation</ns0:begriff></ns0:begriffImKontext><ns0:begriffImKontext><ns0:begriff languageCode="de-DE">zweigleisiger Ausbau</ns0:begriff></ns0:begriffImKontext><ns0:begriffImKontext><ns0:begriff languageCode="de-DE">Plangenehmigung</ns0:begriff></ns0:begriffImKontext><ns0:begriffImKontext><ns0:begriff languageCode="de-DE">Planfeststellungsbeschluss</ns0:begriff></ns0:begriffImKontext><ns0:begriffImKontext><ns0:begriff languageCode="de-DE">Planfeststellungsverfahren</ns0:begriff></ns0:begriffImKontext><ns0:begriffImKontext><ns0:begriff languageCode="de-DE">Planänderung</ns0:begriff></ns0:begriffImKontext><ns0:begriffImKontext><ns0:begriff languageCode="de-DE">Planfeststellung</ns0:begriff></ns0:begriffImKontext><ns0:begriffImKontext><ns0:begriff languageCode="de-DE">Rückbau</ns0:begriff></ns0:begriffImKontext><ns0:begriffImKontext><ns0:begriff languageCode="de-DE">Infrastruktur</ns0:begriff></ns0:begriffImKontext><ns0:begriffImKontext><ns0:begriff languageCode="de-DE">Neubau</ns0:begriff></ns0:begriffImKontext><ns0:begriffImKontext><ns0:begriff languageCode="de-DE">Genehmigung</ns0:begriff></ns0:begriffImKontext><ns0:begriffImKontext><ns0:begriff languageCode="en">Authorization</ns0:begriff></ns0:begriffImKontext><ns0:begriffImKontext><ns0:begriff languageCode="de-DE">Stellungnahme</ns0:begriff></ns0:begriffImKontext><ns0:begriffImKontext><ns0:begriff languageCode="de-DE">Anhörungsverfahren</ns0:begriff></ns0:begriffImKontext><ns0:begriffImKontext><ns0:begriff languageCode="de-DE">Schienenwege</ns0:begriff></ns0:begriffImKontext><ns0:begriffImKontext><ns0:begriff languageCode="de-DE">Träger öffentlicher Belange</ns0:begriff></ns0:begriffImKontext><ns0:begriffImKontext><ns0:begriff languageCode="de-DE">Eisenbahn-Bundesamt</ns0:begriff></ns0:begriffImKontext><ns0:begriffImKontext><ns0:begriff languageCode="de-DE">Plangenehmigungsverfahren</ns0:begriff></ns0:begriffImKontext><ns0:begriffImKontext><ns0:begriff languageCode="de-DE">EBA</ns0:begriff></ns0:begriffImKontext><ns0:begriffImKontext><ns0:begriff languageCode="de-DE">Ausbau</ns0:begriff></ns0:begriffImKontext><ns0:begriffImKontext><ns0:begriff languageCode="de-DE">Öffentlichkeitsbeteiligung</ns0:begriff></ns0:begriffImKontext><ns0:begriffImKontext><ns0:begriff languageCode="de-DE">Umweltverträglichkeitsprüfung</ns0:begriff></ns0:begriffImKontext><ns0:begriffImKontext><ns0:begriff languageCode="de-DE">Einwendung</ns0:begriff></ns0:begriffImKontext><ns0:begriffImKontext><ns0:begriff languageCode="de-DE">UVP</ns0:begriff></ns0:begriffImKontext><ns0:begriffImKontext><ns0:begriff languageCode="de-DE">Einwand</ns0:begriff></ns0:begriffImKontext><ns0:begriffImKontext><ns0:begriff languageCode="de-DE">Einwender</ns0:begriff></ns0:begriffImKontext><ns0:begriffImKontext><ns0:begriff languageCode="de-DE">Einwenderin</ns0:begriff></ns0:begriffImKontext><ns0:begriffImKontext><ns0:begriff languageCode="de-DE">Abstellbahnhof</ns0:begriff></ns0:begriffImKontext><ns0:begriffImKontext><ns0:begriff languageCode="de-DE">Ausbaustrecke</ns0:begriff></ns0:begriffImKontext><ns0:begriffImKontext><ns0:begriff languageCode="de-DE">Außenbahnsteig</ns0:begriff></ns0:begriffImKontext><ns0:begriffImKontext><ns0:begriff languageCode="de-DE">Bahnhof</ns0:begriff></ns0:begriffImKontext><ns0:begriffImKontext><ns0:begriff languageCode="de-DE">Bahnsteig</ns0:begriff></ns0:begriffImKontext><ns0:begriffImKontext><ns0:begriff languageCode="de-DE">Bahnsteigverlängerung</ns0:begriff></ns0:begriffImKontext><ns0:begriffImKontext><ns0:begriff languageCode="de-DE">Bahnübergang</ns0:begriff></ns0:begriffImKontext><ns0:begriffImKontext><ns0:begriff languageCode="de-DE">Behördenbeteiligung</ns0:begriff></ns0:begriffImKontext><ns0:begriffImKontext><ns0:begriff languageCode="de-DE">BeteiligungsverfahrenBetriebswerk</ns0:begriff></ns0:begriffImKontext><ns0:begriffImKontext><ns0:begriff languageCode="de-DE">dreigleisiger Ausbau</ns0:begriff></ns0:begriffImKontext><ns0:begriffImKontext><ns0:begriff languageCode="de-DE">eingleisiger Ausbau</ns0:begriff></ns0:begriffImKontext><ns0:begriffImKontext><ns0:begriff languageCode="de-DE">Eisenbahnknoten</ns0:begriff></ns0:begriffImKontext><ns0:begriffImKontext><ns0:begriff languageCode="de-DE">Eisenbahntunnel</ns0:begriff></ns0:begriffImKontext><ns0:begriffImKontext><ns0:begriff languageCode="de-DE">Eisenbahnüberführung</ns0:begriff></ns0:begriffImKontext><ns0:begriffImKontext><ns0:begriff languageCode="de-DE">Elektrifizierung</ns0:begriff></ns0:begriffImKontext><ns0:begriffImKontext><ns0:begriff languageCode="de-DE">elektronisches Stellwerk</ns0:begriff></ns0:begriffImKontext><ns0:begriffImKontext><ns0:begriff languageCode="de-DE">ESTW</ns0:begriff></ns0:begriffImKontext><ns0:begriffImKontext><ns0:begriff languageCode="de-DE">GSM-R Basisstation</ns0:begriff></ns0:begriffImKontext><ns0:begriffImKontext><ns0:begriff languageCode="de-DE">Haltepunkt</ns0:begriff></ns0:begriffImKontext><ns0:begriffImKontext><ns0:begriff languageCode="de-DE">Kreuzungsbauwerk</ns0:begriff></ns0:begriffImKontext><ns0:begriffImKontext><ns0:begriff languageCode="de-DE">Lärmsanierung</ns0:begriff></ns0:begriffImKontext><ns0:begriffImKontext><ns0:begriff languageCode="de-DE">Lärmschutzwand</ns0:begriff></ns0:begriffImKontext><ns0:begriffImKontext><ns0:begriff languageCode="de-DE">Neubaustrecke</ns0:begriff></ns0:begriffImKontext><ns0:begriffImKontext><ns0:begriff languageCode="de-DE">Rangierbahnhof</ns0:begriff></ns0:begriffImKontext><ns0:begriffImKontext><ns0:begriff languageCode="de-DE">Stellwerk</ns0:begriff></ns0:begriffImKontext><ns0:begriffImKontext><ns0:begriff languageCode="de-DE">Umschlaganlage</ns0:begriff></ns0:begriffImKontext><ns0:begriffImKontext><ns0:begriff languageCode="de-DE">Verkehrsstation</ns0:begriff></ns0:begriffImKontext><ns0:begriffImKontext><ns0:begriff languageCode="de-DE">zweigleisiger Ausbau</ns0:begriff></ns0:begriffImKontext><ns0:begriffImKontext><ns0:begriff languageCode="en">Infrastructure</ns0:begriff></ns0:begriffImKontext></ns0:modulBegriffImKontext><ns0:modulFachlicheFreigabe><ns0:fachlichFreigegebenAm>2025-10-20</ns0:fachlichFreigegebenAm><ns0:fachlichFreigegebenDurch languageCode="de-DE">&lt;p&gt;Bundesministerium für Verkehr (BMV)&lt;/p&gt;</ns0:fachlichFreigegebenDurch><ns0:fachlichFreigegebenDurch languageCode="en">&lt;p&gt;Federal Ministry of Transport (BMV)&lt;/p&gt;</ns0:fachlichFreigegebenDurch></ns0:modulFachlicheFreigabe><ns0:typisierung listURI="urn:de:fim:leika:typisierung" listVersionID="20230116"><code>1</code></ns0:typisierung><ns0:leistungsadressat listURI="urn:xoev-de:fim:codeliste:xzufi.leistungsadressat" listVersionID="1.0"><code>001</code></ns0:leistungsadressat><ns0:leistungsadressat listURI="urn:xoev-de:fim:codeliste:xzufi.leistungsadressat" listVersionID="1.0"><code>003</code></ns0:leistungsadressat><ns0:leistungsadressat listURI="urn:xoev-de:fim:codeliste:xzufi.leistungsadressat" listVersionID="1.0"><code>002</code></ns0:leistungsadressat><ns0:klassifizierung listURI="urn:xoev-de:fim:codeliste:pvlagen" listVersionID="20230308"><code>1100100</code></ns0:klassifizierung><ns0:klassifizierung listURI="urn:xoev-de:fim:codeliste:pvlagen" listVersionID="20230308"><code>2130200</code></ns0:klassifizierung><ns0:klassifizierung listURI="urn:xoev-de:fim:codeliste:pvlagen" listVersionID="20230308"><code>2130100</code></ns0:klassifizierung><ns0:informationsbereichSDG listURI="urn:xoev-de:fim:codeliste:sdginformationsbereich" listVersionID="4"><code>0000000</code></ns0:informationsbereichSDG><ns0:versionsinformation><ns0:erstelltDatumZeit>2022-12-07T09:55:41+01:00</ns0:erstelltDatumZeit><ns0:geaendertDatumZeit>2025-12-01T15:07:42.319000+01:00</ns0:geaendertDatumZeit></ns0:versionsinformation><ns0:sprachversion><ns0:languageCode>de-DE</ns0:languageCode><ns0:sprachbezeichnungDeutsch>Deutsch</ns0:sprachbezeichnungDeutsch><ns0:sprachbezeichnungNativ>Deutsch</ns0:sprachbezeichnungNativ><ns0:erstelltDatumZeit>2017-06-07T06:11:14+02:00</ns0:erstelltDatumZeit><ns0:geaendertDatumZeit>2025-05-14T09:21:24+02:00</ns0:geaendertDatumZeit></ns0:sprachversion><ns0:sprachversion><ns0:languageCode>en</ns0:languageCode><ns0:sprachbezeichnungDeutsch>Englisch</ns0:sprachbezeichnungDeutsch><ns0:sprachbezeichnungNativ>English</ns0:sprachbezeichnungNativ><ns0:erstelltDatumZeit>2025-10-22T06:10:25+02:00</ns0:erstelltDatumZeit><ns0:geaendertDatumZeit>2024-05-30T09:46:12+02:00</ns0:geaendertDatumZeit></ns0:sprachversion></ns0:leistung>
